xterminal/__init__.py
xterminal/multi_client_ssh_terminal.py
xterminal/process.py
xterminal/ssh_process.py
xterminal/ssh_terminal.py
xterminal/terminal.py
xterminal-0.0.2.dist-info/METADATA
xterminal-0.0.2.dist-info/WHEEL
xterminal-0.0.2.dist-info/entry_points.txt
xterminal-0.0.2.dist-info/top_level.txt
xterminal-0.0.2.dist-info/RECORD
